pyaml/__init__.py
pyaml/__main__.py
pyaml/cli.py
pyaml/tests/__init__.py
pyaml/tests/test_cli.py
pyaml/tests/test_dump.py
pyaml-24.12.0.dist-info/COPYING
pyaml-24.12.0.dist-info/METADATA
pyaml-24.12.0.dist-info/WHEEL
pyaml-24.12.0.dist-info/entry_points.txt
pyaml-24.12.0.dist-info/top_level.txt
pyaml-24.12.0.dist-info/RECORD
