Metadata-Version: 2.1
Name: pyaml
Version: 24.12.0
Summary: PyYAML-based module to produce a bit more pretty and readable YAML-serialized data
Home-page: https://github.com/mk-fg/pretty-yaml
Author: Mike Kazantsev
Author-email: Mike Kazantsev <mk.fraggod@gmail.com>
License: WTFPL
Project-URL: Homepage, https://github.com/mk-fg/pretty-yaml
Keywords: yaml,serialization,pretty-print,formatter,human,readability
Classifier: Development Status :: 4 - Beta
Classifier: Intended Audience :: Developers
Classifier: License :: Public Domain
Classifier: Programming Language :: Python
Classifier: Programming Language :: Python :: 3.8
Classifier: Topic :: Software Development
Classifier: Topic :: Software Development :: Libraries :: Python Modules
Classifier: Topic :: Utilities
Requires-Python: >=3.8
License-File: COPYING
Requires-Dist: PyYAML
Provides-Extra: anchors
Requires-Dist: unidecode; extra == "anchors"
